Workbook

Sheet Insights
A1: DATA BLITZ — Inflation on Trial: Drugs & Pharmaceuticals (FY2010–FY2020)
A3: Key numbers (live links)
A4: Pharma companies in panel | B4: =COUNTA('Pharma Companies'!A2:A141) -> 140
A5: Pharma nominal sales CAGR | B5: ='Yearly Analysis'!F16 -> 0.12558741
A6: Pharma price (WPI) CAGR | B6: =WPI!J4 -> 0.030548725
A7: Pharma REAL sales CAGR | B7: ='Yearly Analysis'!G16 -> 0.092221438
A8: Sales multiple FY10->20 | B8: ='Yearly Analysis'!F18 -> 3.2643166
A9: Price multiple FY10->20 | B9: ='Yearly Analysis'!F19 -> 1.3510932
A10: Share of growth that was real | B10: ='Yearly Analysis'!F20 -> 0.74564564
A11: FY2016 pharma growth (economy: -3.5%) | B11: ='Yearly Analysis'!F10 -> 0.13129961
A12: FY2020 pharma growth (economy: -6.5%) | B12: ='Yearly Analysis'!F14 -> 0.081011951
A13: FY2017 pharma growth (the stall) | B13: ='Yearly Analysis'!F11 -> 0.0034292983
A14: Correlation pharma vs economy growth | B14: ='Yearly Analysis'!F22 -> 0.42641951
A15: % pharma cos beating drug inflation | B15: ='Size & Distribution'!G8 -> 0.85
A16: Top-10 share of FY20 sales | B16: ='Top 20 Pharma'!F23 -> 0.51598506
A18: Insights
A19: 1. VERDICT — REAL GROWTH, NOT A PRICE TAG: Pharma sales grew ~3.3x (12.6%/yr) while drug prices rose only ~1.35x (3.1%/yr). Real growth ~9.2%/yr — roughly 3/4 of the growth was genuine volume/mix, about double the all-industry real growth (~4.8%/yr).
A20: 2. DRUG PRICES ARE TAME: Pharma WPI never rose more than ~6% in a year, while all-commodity inflation swung from +9.6% to -3.7%. Drug prices are partly regulated (DPCO/NLEM price caps), so pharma revenue cannot simply ride inflation — growth had to come from volume, new products and exports.
A21: 3. THE CALM INDUSTRY: In FY2016, when total corporate sales fell 3.5% (oil crash), pharma grew +13%. In FY2020, when total sales fell 6.5%, pharma still grew +8%. Correlation with economy-wide growth is low (~0.4) — pharma is defensive: people buy medicines in good and bad times.
A22: 4. THE FY2017–18 STALL: Growth collapsed to ~0-2% for two years, with real sales flat. This was industry-specific, not inflation: commonly cited reasons are US generic price erosion, USFDA regulatory actions on Indian plants, and GST transition in July 2017. Good Q&A talking point.
A23: 5. CONCENTRATION IS RISING: Top 10 companies (Sun, Aurobindo, Cipla, Mylan Labs, Dr. Reddy's, Lupin...) went from ~45% to ~52% of panel sales.
A24: 6. MOST FIRMS WIN: ~85% of pharma companies beat drug-price inflation (vs ~71% across all industries); only ~9% shrank in rupees. Median firm grew ~10.8%/yr.
A25: 7. SMALL FIRMS GREW FASTEST: smallest quartile ~16.7%/yr aggregate vs ~12.4% for the largest. Caveat: survivorship bias — only firms present all 11 years.
A27: Q&A prep:
A28: • Why pharma WPI and not general WPI? Deflating by the industry's own price index measures real volume growth; general WPI is driven by fuel and would mislead.
A29: • How were pharma companies identified? By company name (CSV had no industry code). The Prowess Drugs & Pharmaceuticals industry set would be the cleaner sample.
A30: • Is FY2020-21 (COVID year) included? Pharma WPI for 2020-21 is in the WPI sheet (+2.8%), but the sales file ends Mar 2020.
A31: • Why exclude firms with missing years? Prevents new entrants/exits from inflating or deflating totals.

Sheet Yearly Analysis
A1: Drugs & Pharmaceuticals — sales vs inflation (140 companies reporting every year FY2010-FY2020, Rs crore)
A3: Year | B3: Companies | C3: Total sales (Rs cr) | D3: Pharma WPI | E3: Real sales (FY12 prices) | F3: Nominal growth | G3: Real growth | H3: Pharma inflation | I3: All-industry sales growth* | J3: Price share of growth
A4: FY2010 | B4: =COUNT('Pharma Companies'!C2:C141) -> 140 | C4: =SUM('Pharma Companies'!C2:C141) -> 57912.94 | D4: =WPI!C4 -> 94.22 | E4: =C4/D4*100 -> 61465.655
A5: FY2011 | B5: =COUNT('Pharma Companies'!D2:D141) -> 140 | C5: =SUM('Pharma Companies'!D2:D141) -> 68673.12 | D5: =WPI!C5 -> 96.46 | E5: =C5/D5*100 -> 71193.365 | F5: =C5/C4-1 -> 0.18579924 | G5: =E5/E4-1 -> 0.15826253 | H5: =D5/D4-1 -> 0.023774146 | I5: 0.2252 | J5: =IFERROR(1-G5/F5,"") -> 0.14820676
A6: FY2012 | B6: =COUNT('Pharma Companies'!E2:E141) -> 140 | C6: =SUM('Pharma Companies'!E2:E141) -> 83316.15 | D6: =WPI!C6 -> 100 | E6: =C6/D6*100 -> 83316.15 | F6: =C6/C5-1 -> 0.21322797 | G6: =E6/E5-1 -> 0.1702797 | H6: =D6/D5-1 -> 0.03669915 | I6: 0.2078 | J6: =IFERROR(1-G6/F6,"") -> 0.2014195
A7: FY2013 | B7: =COUNT('Pharma Companies'!F2:F141) -> 140 | C7: =SUM('Pharma Companies'!F2:F141) -> 99448.94 | D7: =WPI!C7 -> 104.8 | E7: =C7/D7*100 -> 94894.027 | F7: =C7/C6-1 -> 0.19363341 | G7: =E7/E6-1 -> 0.13896317 | H7: =D7/D6-1 -> 0.048 | I7: 0.1036 | J7: =IFERROR(1-G7/F7,"") -> 0.28233884
A8: FY2014 | B8: =COUNT('Pharma Companies'!G2:G141) -> 140 | C8: =SUM('Pharma Companies'!G2:G141) -> 115428.76 | D8: =WPI!C8 -> 108.3 | E8: =C8/D8*100 -> 106582.42 | F8: =C8/C7-1 -> 0.16068366 | G8: =E8/E7-1 -> 0.12317311 | H8: =D8/D7-1 -> 0.033396947 | I8: 0.0734 | J8: =IFERROR(1-G8/F8,"") -> 0.23344347
A9: FY2015 | B9: =COUNT('Pharma Companies'!H2:H141) -> 140 | C9: =SUM('Pharma Companies'!H2:H141) -> 133264.98 | D9: =WPI!C9 -> 114.5 | E9: =C9/D9*100 -> 116388.63 | F9: =C9/C8-1 -> 0.15452146 | G9: =E9/E8-1 -> 0.092005883 | H9: =D9/D8-1 -> 0.057248384 | I9: 0.0132 | J9: =IFERROR(1-G9/F9,"") -> 0.40457535
A10: FY2016 | B10: =COUNT('Pharma Companies'!I2:I141) -> 140 | C10: =SUM('Pharma Companies'!I2:I141) -> 150762.62 | D10: =WPI!C10 -> 118.7 | E10: =C10/D10*100 -> 127011.47 | F10: =C10/C9-1 -> 0.13129961 | G10: =E10/E9-1 -> 0.091270475 | H10: =D10/D9-1 -> 0.036681223 | I10: -0.0351 | J10: =IFERROR(1-G10/F10,"") -> 0.30486865
A11: FY2017 | B11: =COUNT('Pharma Companies'!J2:J141) -> 140 | C11: =SUM('Pharma Companies'!J2:J141) -> 151279.63 | D11: =WPI!C11 -> 119.7 | E11: =C11/D11*100 -> 126382.31 | F11: =C11/C10-1 -> 0.0034292983 | G11: =E11/E10-1 -> -0.0049535697 | H11: =D11/D10-1 -> 0.0084245998 | I11: 0.0754 | J11: =IFERROR(1-G11/F11,"") -> 2.4444849
A12: FY2018 | B12: =COUNT('Pharma Companies'!K2:K141) -> 140 | C12: =SUM('Pharma Companies'!K2:K141) -> 154058.54 | D12: =WPI!C12 -> 121.2 | E12: =C12/D12*100 -> 127111.01 | F12: =C12/C11-1 -> 0.01836936 | G12: =E12/E11-1 -> 0.0057657789 | H12: =D12/D11-1 -> 0.012531328 | I12: 0.0806 | J12: =IFERROR(1-G12/F12,"") -> 0.68611977
A13: FY2019 | B13: =COUNT('Pharma Companies'!L2:L141) -> 140 | C13: =SUM('Pharma Companies'!L2:L141) -> 174878.89 | D13: =WPI!C13 -> 123.5 | E13: =C13/D13*100 -> 141602.34 | F13: =C13/C12-1 -> 0.13514571 | G13: =E13/E12-1 -> 0.11400534 | H13: =D13/D12-1 -> 0.018976898 | I13: 0.1523 | J13: =IFERROR(1-G13/F13,"") -> 0.15642647
A14: FY2020 | B14: =COUNT('Pharma Companies'!M2:M141) -> 140 | C14: =SUM('Pharma Companies'!M2:M141) -> 189046.17 | D14: =WPI!C14 -> 127.3 | E14: =C14/D14*100 -> 148504.45 | F14: =C14/C13-1 -> 0.081011951 | G14: =E14/E13-1 -> 0.048742937 | H14: =D14/D13-1 -> 0.030769231 | I14: -0.0651 | J14: =IFERROR(1-G14/F14,"") -> 0.39832411
A16: FY10-20 CAGR | F16: =(C14/C4)^(1/10)-1 -> 0.12558741 | G16: =(E14/E4)^(1/10)-1 -> 0.092221438 | H16: =(D14/D4)^(1/10)-1 -> 0.030548725
A18: Sales multiple FY10->FY20 | F18: =C14/C4 -> 3.2643166
A19: Price multiple (pharma WPI) | F19: =D14/D4 -> 1.3510932
A20: Share of growth that was real (log) | F20: =LN(E14/E4)/LN(C14/C4) -> 0.74564564
A21: Correlation: pharma sales growth vs pharma inflation | F21: =CORREL(F5:F14,H5:H14) -> 0.68277504
A22: Correlation: pharma growth vs all-industry growth | F22: =CORREL(F5:F14,I5:I14) -> 0.42641951
A23: Volatility (std dev) of pharma growth | F23: =STDEV(F5:F14) -> 0.071871526
A24: Volatility (std dev) of all-industry growth | F24: =STDEV(I5:I14) -> 0.095412264
A25: Pharma CAGR FY10-14 | F25: =(C8/C4)^(1/4)-1 -> 0.18818647
A26: Pharma CAGR FY14-20 | F26: =(C14/C8)^(1/6)-1 -> 0.085697844
A28: * All-industry growth = 3,091 companies (all sectors) from the same CMIE file, computed in the earlier analysis — used as the "economy" benchmark.
A29: Pharma companies identified by company name (pharma/drug/laboratories/remedies/lifesciences etc. + known majors) because the CSV has no industry code; FMCG names like Dabur/P&G removed.

Sheet Size & Distribution
A1: Which pharma companies beat drug-price inflation? (FY10-20 CAGR)
A3: Size quartile | B3: Companies | C3: FY10 sales (Rs cr) | D3: FY20 sales (Rs cr) | E3: Aggregate CAGR | F3: Median company CAGR | G3: % beating pharma inflation
A4: Small | B4: =COUNTIF('Pharma Companies'!$B$2:$B$141,"Small") -> 35 | C4: =SUMIF('Pharma Companies'!$B$2:$B$141,"Small",'Pharma Companies'!$C$2:$C$141) -> 503.45 | D4: =SUMIF('Pharma Companies'!$B$2:$B$141,"Small",'Pharma Companies'!$M$2:$M$141) -> 2350.75 | E4: =(D4/C4)^(1/10)-1 -> 0.16660816 | F4: 0.1399 | G4: =COUNTIFS('Pharma Companies'!$B$2:$B$141,"Small",'Pharma Companies'!$P$2:$P$141,"Yes")/B4 -> 0.94285714
A5: Lower-mid | B5: =COUNTIF('Pharma Companies'!$B$2:$B$141,"Lower-mid") -> 35 | C5: =SUMIF('Pharma Companies'!$B$2:$B$141,"Lower-mid",'Pharma Companies'!$C$2:$C$141) -> 2548.26 | D5: =SUMIF('Pharma Companies'!$B$2:$B$141,"Lower-mid",'Pharma Companies'!$M$2:$M$141) -> 7857.34 | E5: =(D5/C5)^(1/10)-1 -> 0.11918835 | F5: 0.1067 | G5: =COUNTIFS('Pharma Companies'!$B$2:$B$141,"Lower-mid",'Pharma Companies'!$P$2:$P$141,"Yes")/B5 -> 0.85714286
A6: Upper-mid | B6: =COUNTIF('Pharma Companies'!$B$2:$B$141,"Upper-mid") -> 35 | C6: =SUMIF('Pharma Companies'!$B$2:$B$141,"Upper-mid",'Pharma Companies'!$C$2:$C$141) -> 7960.14 | D6: =SUMIF('Pharma Companies'!$B$2:$B$141,"Upper-mid",'Pharma Companies'!$M$2:$M$141) -> 27379.64 | E6: =(D6/C6)^(1/10)-1 -> 0.13148995 | F6: 0.0964 | G6: =COUNTIFS('Pharma Companies'!$B$2:$B$141,"Upper-mid",'Pharma Companies'!$P$2:$P$141,"Yes")/B6 -> 0.77142857
A7: Large | B7: =COUNTIF('Pharma Companies'!$B$2:$B$141,"Large") -> 35 | C7: =SUMIF('Pharma Companies'!$B$2:$B$141,"Large",'Pharma Companies'!$C$2:$C$141) -> 46901.09 | D7: =SUMIF('Pharma Companies'!$B$2:$B$141,"Large",'Pharma Companies'!$M$2:$M$141) -> 151458.44 | E7: =(D7/C7)^(1/10)-1 -> 0.12437467 | F7: 0.1048 | G7: =COUNTIFS('Pharma Companies'!$B$2:$B$141,"Large",'Pharma Companies'!$P$2:$P$141,"Yes")/B7 -> 0.82857143
A8: All | B8: =COUNTIF('Pharma Companies'!$B$2:$B$141,"*") -> 140 | C8: =SUMIF('Pharma Companies'!$B$2:$B$141,"*",'Pharma Companies'!$C$2:$C$141) -> 57912.94 | D8: =SUMIF('Pharma Companies'!$B$2:$B$141,"*",'Pharma Companies'!$M$2:$M$141) -> 189046.17 | E8: =(D8/C8)^(1/10)-1 -> 0.12558741 | F8: 0.108 | G8: =COUNTIFS('Pharma Companies'!$B$2:$B$141,"*",'Pharma Companies'!$P$2:$P$141,"Yes")/B8 -> 0.85
A10: Median column computed in Python; all other cells are live formulas on the Pharma Companies sheet.
A12: Company CAGR band | B12: Companies | C12: Share
A13: Shrank in rupees (<0%) | B13: =COUNTIF('Pharma Companies'!$N$2:$N$141,"<0") -> 12 | C13: =B13/SUM($B$13:$B$17) -> 0.085714286
A14: Grew, but below pharma inflation | B14: =COUNTIFS('Pharma Companies'!$N$2:$N$141,">=0",'Pharma Companies'!$O$2:$O$141,"<=0") -> 9 | C14: =B14/SUM($B$13:$B$17) -> 0.064285714
A15: Beat inflation, under 10% | B15: =COUNTIFS('Pharma Companies'!$O$2:$O$141,">0",'Pharma Companies'!$N$2:$N$141,"<0.1") -> 40 | C15: =B15/SUM($B$13:$B$17) -> 0.28571429
A16: 10% to 20% | B16: =COUNTIFS('Pharma Companies'!$N$2:$N$141,">=0.1",'Pharma Companies'!$N$2:$N$141,"<0.2") -> 59 | C16: =B16/SUM($B$13:$B$17) -> 0.42142857
A17: Over 20% | B17: =COUNTIF('Pharma Companies'!$N$2:$N$141,">=0.2") -> 20 | C17: =B17/SUM($B$13:$B$17) -> 0.14285714
A19: FY2020: % of pharma companies with falling sales | C19: =COUNTIF('Pharma Companies'!Q2:Q141,"<0")/140 -> 0.33571429

Sheet Top 20 Pharma
A1: =-'Yearly Analysis'!AA46 -> 0 | B1: FY10 sales (Rs cr) | C1: FY20 sales (Rs cr) | D1: CAGR | E1: Real CAGR | F1: Share of FY20 total
A2: Sun Pharmaceutical Inds. Ltd. | B2: 1853 | C2: 13136 | D2: =(C2/B2)^(1/10)-1 -> 0.2163506 | E2: =(1+D2)/(1+WPI!$J$5)-1 -> 0.18029411 | F2: =C2/SUM('Pharma Companies'!$M$2:$M$141) -> 0.069485671
A3: Aurobindo Pharma Ltd. | B3: 3130 | C3: 13022 | D3: =(C3/B3)^(1/10)-1 -> 0.15322311 | E3: =(1+D3)/(1+WPI!$J$5)-1 -> 0.11903792 | F3: =C3/SUM('Pharma Companies'!$M$2:$M$141) -> 0.068882644
A4: Cipla Ltd. | B4: 5412 | C4: 12220 | D4: =(C4/B4)^(1/10)-1 -> 0.084854118 | E4: =(1+D4)/(1+WPI!$J$5)-1 -> 0.052695609 | F4: =C4/SUM('Pharma Companies'!$M$2:$M$141) -> 0.064640294
A5: Mylan Laboratories Ltd. | B5: 1867 | C5: 11609 | D5: =(C5/B5)^(1/10)-1 -> 0.20050797 | E5: =(1+D5)/(1+WPI!$J$5)-1 -> 0.16492112 | F5: =C5/SUM('Pharma Companies'!$M$2:$M$141) -> 0.061408279
A6: Dr. Reddy'S Laboratories Ltd. | B6: 4248 | C6: 10992 | D6: =(C6/B6)^(1/10)-1 -> 0.099737973 | E6: =(1+D6)/(1+WPI!$J$5)-1 -> 0.06713826 | F6: =C6/SUM('Pharma Companies'!$M$2:$M$141) -> 0.058144526
A7: Lupin Ltd. | B7: 3107 | C7: 10633 | D7: =(C7/B7)^(1/10)-1 -> 0.13091888 | E7: =(1+D7)/(1+WPI!$J$5)-1 -> 0.09739487 | F7: =C7/SUM('Pharma Companies'!$M$2:$M$141) -> 0.056245519
A8: Hetero Labs Ltd. | B8: 1343 | C8: 6775 | D8: =(C8/B8)^(1/10)-1 -> 0.17566429 | E8: =(1+D8)/(1+WPI!$J$5)-1 -> 0.14081388 | F8: =C8/SUM('Pharma Companies'!$M$2:$M$141) -> 0.035837806
A9: Alkem Laboratories Ltd. | B9: 993 | C9: 6719 | D9: =(C9/B9)^(1/10)-1 -> 0.2106972 | E9: =(1+D9)/(1+WPI!$J$5)-1 -> 0.17480831 | F9: =C9/SUM('Pharma Companies'!$M$2:$M$141) -> 0.035541582
A10: Glenmark Pharmaceuticals Ltd. | B10: 1028 | C10: 6413 | D10: =(C10/B10)^(1/10)-1 -> 0.20089991 | E10: =(1+D10)/(1+WPI!$J$5)-1 -> 0.16530144 | F10: =C10/SUM('Pharma Companies'!$M$2:$M$141) -> 0.03392293
A11: Torrent Pharmaceuticals Ltd. | B11: 1374 | C11: 6026 | D11: =(C11/B11)^(1/10)-1 -> 0.15932243 | E11: =(1+D11)/(1+WPI!$J$5)-1 -> 0.12495645 | F11: =C11/SUM('Pharma Companies'!$M$2:$M$141) -> 0.031875811
A12: Zydus Lifesciences Ltd. | B12: 1550 | C12: 5971 | D12: =(C12/B12)^(1/10)-1 -> 0.14438337 | E12: =(1+D12)/(1+WPI!$J$5)-1 -> 0.11046022 | F12: =C12/SUM('Pharma Companies'!$M$2:$M$141) -> 0.031584877
A13: Divi'S Laboratories Ltd. | B13: 935 | C13: 5198 | D13: =(C13/B13)^(1/10)-1 -> 0.18714144 | E13: =(1+D13)/(1+WPI!$J$5)-1 -> 0.15195081 | F13: =C13/SUM('Pharma Companies'!$M$2:$M$141) -> 0.027495929
... A21: Abbott India Ltd. | B21: 339 | C21: 2427 | D21: =(C21/B21)^(1/10)-1 -> 0.21755057 | E21: =(1+D21)/(1+WPI!$J$5)-1 -> 0.18145852 | F21: =C21/SUM('Pharma Companies'!$M$2:$M$141) -> 0.012838134
A23: Top 10 share of FY20 pharma sales | F23: =SUM(F2:F11) -> 0.51598506

Sheet WPI
A1: Wholesale Price Index — Pharma vs economy (spliced, 2011-12 = 100)
A3: Year | B3: CMIE column | C3: WPI Pharmaceuticals (Drugs & medicines) | D3: WPI All commodities | E3: WPI Manufactured products | F3: Pharma inflation | G3: All-commodity inflation
A4: 2009-10 | B4: Mar 2010 | C4: 94.22 | D4: 83.78 | E4: 88.2 | I4: Pharma WPI CAGR FY10-20 | J4: =(C14/C4)^(1/10)-1 -> 0.030548725
A5: 2010-11 | B5: Mar 2011 | C5: 96.46 | D5: 91.8 | E5: 93.23 | F5: =C5/C4-1 -> 0.023774146 | G5: =D5/D4-1 -> 0.095726904 | I5: Pharma WPI CAGR (used for real) | J5: =J4 -> 0.030548725
A6: 2011-12 | B6: Mar 2012 | C6: 100 | D6: 100 | E6: 100 | F6: =C6/C5-1 -> 0.03669915 | G6: =D6/D5-1 -> 0.089324619 | I6: All-commodity WPI CAGR FY10-20 | J6: =(D14/D4)^(1/10)-1 -> 0.038127494
A7: 2012-13 | B7: Mar 2013 | C7: 104.8 | D7: 106.9 | E7: 105.3 | F7: =C7/C6-1 -> 0.048 | G7: =D7/D6-1 -> 0.069
A8: 2013-14 | B8: Mar 2014 | C8: 108.3 | D8: 112.5 | E8: 108.5 | F8: =C8/C7-1 -> 0.033396947 | G8: =D8/D7-1 -> 0.052385407
A9: 2014-15 | B9: Mar 2015 | C9: 114.5 | D9: 113.9 | E9: 111.2 | F9: =C9/C8-1 -> 0.057248384 | G9: =D9/D8-1 -> 0.012444444
A10: 2015-16 | B10: Mar 2016 | C10: 118.7 | D10: 109.7 | E10: 109.2 | F10: =C10/C9-1 -> 0.036681223 | G10: =D10/D9-1 -> -0.036874451
A11: 2016-17 | B11: Mar 2017 | C11: 119.7 | D11: 111.6 | E11: 110.7 | F11: =C11/C10-1 -> 0.0084245998 | G11: =D11/D10-1 -> 0.017319964
A12: 2017-18 | B12: Mar 2018 | C12: 121.2 | D12: 114.9 | E12: 113.8 | F12: =C12/C11-1 -> 0.012531328 | G12: =D12/D11-1 -> 0.029569892
A13: 2018-19 | B13: Mar 2019 | C13: 123.5 | D13: 119.8 | E13: 117.9 | F13: =C13/C12-1 -> 0.018976898 | G13: =D13/D12-1 -> 0.042645779
A14: 2019-20 | B14: Mar 2020 | C14: 127.3 | D14: 121.8 | E14: 118.3 | F14: =C14/C13-1 -> 0.030769231 | G14: =D14/D13-1 -> 0.016694491
A15: 2020-21 | B15: Mar 2021 | C15: 130.9 | D15: 123.4 | E15: 121.5 | F15: =C15/C14-1 -> 0.028279654 | G15: =D15/D14-1 -> 0.013136289
A17: Source: Office of Economic Adviser, DPIIT (eaindustry.nic.in) annual financial-year WPI files.
A18: 2012-13 onward: Base 2011-12 series, "Manufacture of pharmaceuticals, medicinal chemical and botanical products" (code 1311000000).
A19: 2009-10 to 2011-12: Base 2004-05 series "Drugs & medicines" (code 1308060000), rescaled so 2011-12 = 100. All-commodity/Manufactured rescaled the same way.
A20: 2020-21 index included for reference; the CMIE sales file supplied ends at Mar 2020, so FY2021 sales are not in this analysis.

Sheet Pharma Companies
A1: Company | B1: Size quartile (FY10 sales) | C1: FY2010 | D1: FY2011 | E1: FY2012 | F1: FY2013 | G1: FY2014 | H1: FY2015 | I1: FY2016 | J1: FY2017 | K1: FY2018 | L1: FY2019 | M1: FY2020 | N1: CAGR FY10-20 | O1: Real CAGR (pharma WPI) | P1: Beat pharma inflation? | Q1: FY20 growth
A2: Aarti Drugs Ltd. | B2: Large | C2: 485.77 | D2: 504.88 | E2: 675.6 | F2: 872.51 | G2: 1027.3 | H2: 1147.8 | I2: 1144.02 | J2: 1163.29 | K2: 1145.57 | L2: 1436.42 | M2: 1619.66 | N2: =(M2/C2)^(1/10)-1 -> 0.12797459 | O2: =(1+N2)/(1+WPI!$J$5)-1 -> 0.094537855 | P2: =IF(O2>0,"Yes","No") -> Yes | Q2: =M2/L2-1 -> 0.12756715
A3: Abbott India Ltd. | B3: Upper-mid | C3: 339.34 | D3: 170.5 | E3: 870.3 | F3: 960.53 | G3: 1383.91 | H3: 1335.71 | I3: 1538.86 | J3: 1688.6 | K3: 1893.11 | L3: 2097.66 | M3: 2427.26 | N3: =(M3/C3)^(1/10)-1 -> 0.21744156 | O3: =(1+N3)/(1+WPI!$J$5)-1 -> 0.18135274 | P3: =IF(O3>0,"Yes","No") -> Yes | Q3: =M3/L3-1 -> 0.15712747
A4: Agio Pharmaceuticals Ltd. | B4: Lower-mid | C4: 91.71 | D4: 138.45 | E4: 190.87 | F4: 265.29 | G4: 226.76 | H4: 232.03 | I4: 237.71 | J4: 221.26 | K4: 206.25 | L4: 144.52 | M4: 107.09 | N4: =(M4/C4)^(1/10)-1 -> 0.015624625 | O4: =(1+N4)/(1+WPI!$J$5)-1 -> -0.014481702 | P4: =IF(O4>0,"Yes","No") -> No | Q4: =M4/L4-1 -> -0.25899529
A5: Agog Pharma Ltd. | B5: Small | C5: 27.62 | D5: 25.39 | E5: 36.44 | F5: 53.59 | G5: 58.17 | H5: 61.76 | I5: 64.5 | J5: 70.58 | K5: 65.12 | L5: 50.45 | M5: 69.6 | N5: =(M5/C5)^(1/10)-1 -> 0.09682807 | O5: =(1+N5)/(1+WPI!$J$5)-1 -> 0.064314616 | P5: =IF(O5>0,"Yes","No") -> Yes | Q5: =M5/L5-1 -> 0.37958375
A6: Agribiotech Industries Ltd. | B6: Lower-mid | C6: 91.3 | D6: 97.53 | E6: 117.67 | F6: 185.83 | G6: 243.75 | H6: 281.62 | I6: 221.09 | J6: 188.87 | K6: 136.38 | L6: 168.1 | M6: 183.88 | N6: =(M6/C6)^(1/10)-1 -> 0.072522401 | O6: =(1+N6)/(1+WPI!$J$5)-1 -> 0.040729443 | P6: =IF(O6>0,"Yes","No") -> Yes | Q6: =M6/L6-1 -> 0.093872695
A7: Ahlcon Parenterals (India) Ltd. | B7: Small | C7: 31.53 | D7: 38.81 | E7: 55.1 | F7: 81.36 | G7: 95.23 | H7: 126.69 | I7: 133.22 | J7: 149.27 | K7: 150.7 | L7: 125.41 | M7: 149.83 | N7: =(M7/C7)^(1/10)-1 -> 0.16865812 | O7: =(1+N7)/(1+WPI!$J$5)-1 -> 0.1340154 | P7: =IF(O7>0,"Yes","No") -> Yes | Q7: =M7/L7-1 -> 0.19472131
A8: Aimil Pharmaceuticals (India) Ltd. | B8: Lower-mid | C8: 71.1 | D8: 72.39 | E8: 90.8 | F8: 103.4 | G8: 136.25 | H8: 155.69 | I8: 189.29 | J8: 280.23 | K8: 282.01 | L8: 304.58 | M8: 291.76 | N8: =(M8/C8)^(1/10)-1 -> 0.15163701 | O8: =(1+N8)/(1+WPI!$J$5)-1 -> 0.11749885 | P8: =IF(O8>0,"Yes","No") -> Yes | Q8: =M8/L8-1 -> -0.042090748
A9: Ajanta Pharma Ltd. | B9: Upper-mid | C9: 385 | D9: 393.63 | E9: 541.56 | F9: 772.47 | G9: 1002.1 | H9: 1209.37 | I9: 1395.34 | J9: 1571.11 | K9: 1561.77 | L9: 1493.94 | M9: 1892.25 | N9: =(M9/C9)^(1/10)-1 -> 0.1726051 | O9: =(1+N9)/(1+WPI!$J$5)-1 -> 0.13784537 | P9: =IF(O9>0,"Yes","No") -> Yes | Q9: =M9/L9-1 -> 0.26661713
A10: Akums Drugs & Pharmaceuticals Ltd. | B10: Upper-mid | C10: 410.93 | D10: 570.95 | E10: 646.88 | F10: 789.28 | G10: 888.46 | H10: 929.66 | I10: 547.72 | J10: 610.42 | K10: 567.29 | L10: 685.5 | M10: 736.91 | N10: =(M10/C10)^(1/10)-1 -> 0.060143513 | O10: =(1+N10)/(1+WPI!$J$5)-1 -> 0.028717505 | P10: =IF(O10>0,"Yes","No") -> Yes | Q10: =M10/L10-1 -> 0.074996353
A11: Alkem Laboratories Ltd. | B11: Large | C11: 992.98 | D11: 1668.78 | E11: 1973.52 | F11: 2335.29 | G11: 2700.19 | H11: 3174.29 | I11: 3897.1 | J11: 4603.04 | K11: 5196.7 | L11: 5759.9 | M11: 6719.33 | N11: =(M11/C11)^(1/10)-1 -> 0.21070559 | O11: =(1+N11)/(1+WPI!$J$5)-1 -> 0.17481644 | P11: =IF(O11>0,"Yes","No") -> Yes | Q11: =M11/L11-1 -> 0.1665706
A12: Alpa Laboratories Ltd. | B12: Lower-mid | C12: 91.72 | D12: 81.28 | E12: 51.3 | F12: 54.28 | G12: 51.67 | H12: 56.33 | I12: 54.59 | J12: 61.32 | K12: 60.99 | L12: 75.9 | M12: 84.73 | N12: =(M12/C12)^(1/10)-1 -> -0.0078957364 | O12: =(1+N12)/(1+WPI!$J$5)-1 -> -0.037304846 | P12: =IF(O12>0,"Yes","No") -> No | Q12: =M12/L12-1 -> 0.11633729
A13: Alta Laboratories Ltd. | B13: Lower-mid | C13: 47.32 | D13: 56.42 | E13: 64.94 | F13: 75.55 | G13: 92.05 | H13: 105.25 | I13: 114.77 | J13: 124.06 | K13: 122.7 | L13: 169.76 | M13: 176.82 | N13: =(M13/C13)^(1/10)-1 -> 0.14090285 | O13: =(1+N13)/(1+WPI!$J$5)-1 -> 0.10708288 | P13: =IF(O13>0,"Yes","No") -> Yes | Q13: =M13/L13-1 -> 0.041588124
... A141: Zydus Wellness Ltd. | B141: Upper-mid | C141: 164.47 | D141: 200.89 | E141: 209.54 | F141: 120.85 | G141: 113.99 | H141: 113.38 | I141: 105.24 | J141: 114.77 | K141: 136.84 | L141: 159.65 | M141: 165.31 | N141: =(M141/C141)^(1/10)-1 -> 0.00050956141 | O141: =(1+N141)/(1+WPI!$J$5)-1 -> -0.029148708 | P141: =IF(O141>0,"Yes","No") -> No | Q141: =M141/L141-1 -> 0.035452552
